{"content":[{"id":"3771317c","settings":{"layout":"full_width","gap":"no","height":"min-height","custom_height":{"unit":"px","size":"380","sizes":[]},"column_position":"stretch","background_background":"classic","__globals__":{"background_color":"globals\/colors?id=secondary"},"content_position":"middle","custom_height_tablet":{"unit":"px","size":"250","sizes":[]},"custom_height_mobile":{"unit":"px","size":"150","sizes":[]},"overflow":"hidden","_title":"Hero"},"elements":[{"id":"52a11c66","settings":{"_column_size":"100","content_position":"center"},"elements":[{"id":"aeebcd0","settings":{"title":"Music Music Music Music","title_color":"#FFFFFF","__globals__":{"title_color":"globals\/colors?id=415489b","typography_typography":"globals\/typography?id=primary"},"align":"center","_margin_tablet":{"unit":"px","top":"0","right":"-100","bottom":"0","left":"-100","isLinked":""},"header_size":"h1"},"elements":[],"isInner":false,"widgetType":"heading","elType":"widget"}],"isInner":"","elType":"column"}],"isInner":"","elType":"section"},{"id":"63f6eca4","settings":{"height":"min-height","custom_height":{"unit":"px","size":"567","sizes":[]},"column_position":"stretch","structure":"20","gap":"wider","padding":{"unit":"px","top":"75","right":"0","bottom":"0","left":"0","isLinked":""},"margin":{"unit":"px","top":"0","right":"0","bottom":"270","left":"0","isLinked":""},"overflow":"hidden","margin_tablet":{"unit":"px","top":"0","right":"0","bottom":"150","left":"0","isLinked":""},"margin_mobile":{"unit":"px","top":"0","right":"0","bottom":"50","left":"0","isLinked":""},"padding_mobile":{"unit":"px","top":"50","right":"0","bottom":"0","left":"0","isLinked":""},"_title":"Albums"},"elements":[{"id":"41876de3","settings":{"_column_size":"50","_inline_size_tablet":"40"},"elements":[{"id":"6698be40","settings":{"graphic_element":"image","image":{"url":"","id":""},"image_size":"full","selected_icon":{"value":"","library":""},"title_text_a":"","description_text_a":"","background_a_background":"classic","background_a_position":"center center","background_a_repeat":"no-repeat","background_a_size":"cover","title_text_b":"2020","description_text_b":"Stop Talking","button_text":"Listen","background_b_background":"classic","vertical_position_a":"middle","image_width":{"unit":"%","size":"100","sizes":[]},"image_opacity":{"unit":"px","size":"","sizes":[]},"background_a_image":{"url":"https:\/\/library.elementor.com\/music-artist\/wp-content\/uploads\/sites\/116\/2020\/10\/album1.jpg","id":"95"},"background_b_color":"#000000BD","height":{"unit":"px","size":"530","sizes":[]},"flip_effect":"fade","title_color_b":"#FFFFFF","title_typography_b_typography":"custom","title_typography_b_font_family":"Anton","title_typography_b_font_size":{"unit":"px","size":"20","sizes":[]},"title_typography_b_font_weight":"400","title_typography_b_text_transform":"uppercase","title_typography_b_font_style":"normal","title_typography_b_line_height":{"unit":"px","size":"30","sizes":[]},"title_typography_b_letter_spacing":{"unit":"px","size":"1.33","sizes":[]},"description_color_b":"#FFFFFF","button_size":"xs","button_border_width":{"unit":"px","size":"0","sizes":[]},"button_border_radius":{"unit":"px","size":"0","sizes":[]},"__globals__":{"background_b_color":"globals\/colors?id=d615ad7","title_color_b":"globals\/colors?id=415489b","title_typography_b_typography":"globals\/typography?id=0fa9cde","description_color_b":"globals\/colors?id=415489b","description_typography_b_typography":"globals\/typography?id=secondary","button_typography_typography":"globals\/typography?id=accent","button_text_color":"globals\/colors?id=accent","button_background_color":"globals\/colors?id=secondary","button_hover_text_color":"globals\/colors?id=secondary","button_hover_background_color":"globals\/colors?id=accent"},"__dynamic__":{"link":"[elementor-tag id=\"7ccc71d\" name=\"popup\" settings=\"%7B%22popup%22%3A%22120%22%7D\"]"},"height_tablet":{"unit":"px","size":"250","sizes":[]},"height_mobile":{"unit":"px","size":"295","sizes":[]}},"elements":[],"isInner":false,"widgetType":"flip-box","elType":"widget"},{"id":"4635c147","settings":{"graphic_element":"image","image":{"url":"","id":""},"image_size":"full","selected_icon":{"value":"","library":""},"title_text_a":"","description_text_a":"","background_a_background":"classic","background_a_position":"center center","background_a_repeat":"no-repeat","background_a_size":"cover","title_text_b":"2018","description_text_b":"Final Girl","button_text":"Listen","background_b_background":"classic","vertical_position_a":"middle","image_width":{"unit":"%","size":"100","sizes":[]},"image_opacity":{"unit":"px","size":"","sizes":[]},"background_a_image":{"url":"https:\/\/library.elementor.com\/music-artist\/wp-content\/uploads\/sites\/116\/2020\/10\/album3.jpg","id":"97"},"background_b_color":"#000000BD","height":{"unit":"px","size":"530","sizes":[]},"flip_effect":"fade","title_color_b":"#FFFFFF","title_typography_b_typography":"custom","title_typography_b_font_family":"Anton","title_typography_b_font_size":{"unit":"px","size":"20","sizes":[]},"title_typography_b_font_weight":"400","title_typography_b_text_transform":"uppercase","title_typography_b_font_style":"normal","title_typography_b_line_height":{"unit":"px","size":"30","sizes":[]},"title_typography_b_letter_spacing":{"unit":"px","size":"1.33","sizes":[]},"description_color_b":"#FFFFFF","button_size":"xs","button_border_width":{"unit":"px","size":"0","sizes":[]},"button_border_radius":{"unit":"px","size":"0","sizes":[]},"_margin":{"unit":"px","top":"40","right":"0","bottom":"0","left":"0","isLinked":""},"__globals__":{"background_b_color":"globals\/colors?id=d615ad7","title_color_b":"globals\/colors?id=415489b","title_typography_b_typography":"globals\/typography?id=0fa9cde","description_color_b":"globals\/colors?id=415489b","description_typography_b_typography":"globals\/typography?id=secondary","button_typography_typography":"globals\/typography?id=accent","button_text_color":"globals\/colors?id=accent","button_background_color":"globals\/colors?id=secondary","button_hover_text_color":"globals\/colors?id=secondary","button_hover_background_color":"globals\/colors?id=accent"},"height_tablet":{"unit":"px","size":"250","sizes":[]},"height_mobile":{"unit":"px","size":"295","sizes":[]},"__dynamic__":{"link":"[elementor-tag id=\"b9036dd\" name=\"popup\" settings=\"%7B%22popup%22%3A%22120%22%7D\"]"}},"elements":[],"isInner":false,"widgetType":"flip-box","elType":"widget"},{"id":"22ab35d","settings":{"graphic_element":"image","image":{"url":"","id":""},"image_size":"full","selected_icon":{"value":"","library":""},"title_text_a":"","description_text_a":"","background_a_background":"classic","background_a_position":"center center","background_a_repeat":"no-repeat","background_a_size":"cover","title_text_b":"2014","description_text_b":"Tears of Joy","button_text":"Listen","background_b_background":"classic","vertical_position_a":"middle","image_width":{"unit":"%","size":"100","sizes":[]},"image_opacity":{"unit":"px","size":"","sizes":[]},"background_a_image":{"url":"https:\/\/library.elementor.com\/music-artist\/wp-content\/uploads\/sites\/116\/2020\/10\/album5.jpg","id":"99"},"background_b_color":"#000000BD","height":{"unit":"px","size":"530","sizes":[]},"flip_effect":"fade","title_color_b":"#FFFFFF","title_typography_b_typography":"custom","title_typography_b_font_family":"Anton","title_typography_b_font_size":{"unit":"px","size":"20","sizes":[]},"title_typography_b_font_weight":"400","title_typography_b_text_transform":"uppercase","title_typography_b_font_style":"normal","title_typography_b_line_height":{"unit":"px","size":"30","sizes":[]},"title_typography_b_letter_spacing":{"unit":"px","size":"1.33","sizes":[]},"description_color_b":"#FFFFFF","button_size":"xs","button_border_width":{"unit":"px","size":"0","sizes":[]},"button_border_radius":{"unit":"px","size":"0","sizes":[]},"_margin":{"unit":"px","top":"40","right":"0","bottom":"0","left":"0","isLinked":""},"__globals__":{"background_b_color":"globals\/colors?id=d615ad7","title_color_b":"globals\/colors?id=415489b","title_typography_b_typography":"globals\/typography?id=0fa9cde","description_color_b":"globals\/colors?id=415489b","description_typography_b_typography":"globals\/typography?id=secondary","button_typography_typography":"globals\/typography?id=accent","button_text_color":"globals\/colors?id=accent","button_background_color":"globals\/colors?id=secondary","button_hover_text_color":"globals\/colors?id=secondary","button_hover_background_color":"globals\/colors?id=accent"},"height_tablet":{"unit":"px","size":"250","sizes":[]},"height_mobile":{"unit":"px","size":"295","sizes":[]},"__dynamic__":{"link":"[elementor-tag id=\"366188c\" name=\"popup\" settings=\"%7B%22popup%22%3A%22120%22%7D\"]"}},"elements":[],"isInner":false,"widgetType":"flip-box","elType":"widget"}],"isInner":"","elType":"column"},{"id":"373dcb6f","settings":{"_column_size":"50","_inline_size_tablet":"40"},"elements":[{"id":"4760b6f7","settings":{"icon_list":[{"text":"Facebook","selected_icon":{"value":"","library":""},"_id":"a98e94a"},{"text":"Instagram","selected_icon":{"value":"","library":""},"_id":"bc5519e"},{"text":"Soundcloud","selected_icon":{"value":"","library":""},"_id":"fb9428b"},{"text":"Spotify","selected_icon":{"value":"","library":""},"_id":"a24e714"},{"text":"Youtube","selected_icon":{"value":"","library":""},"_id":"4e71b42"}],"space_between":{"unit":"px","size":"20","sizes":[]},"_element_width":"auto","_position":"absolute","_offset_orientation_h":"end","_offset_x_end":{"unit":"px","size":"-180","sizes":[]},"__globals__":{"text_color":"globals\/colors?id=primary","icon_typography_typography":"globals\/typography?id=0fa9cde","text_color_hover":"globals\/colors?id=secondary"},"_offset_x_end_tablet":{"unit":"px","size":"-140","sizes":[]},"hide_mobile":"hidden-phone"},"elements":[],"isInner":false,"widgetType":"icon-list","elType":"widget"},{"id":"5352509e","settings":{"graphic_element":"image","image":{"url":"","id":""},"image_size":"full","selected_icon":{"value":"","library":""},"title_text_a":"","description_text_a":"","background_a_background":"classic","background_a_position":"center center","background_a_repeat":"no-repeat","background_a_size":"cover","title_text_b":"2019","description_text_b":"Horizon","button_text":"Listen","background_b_background":"classic","vertical_position_a":"middle","image_width":{"unit":"%","size":"100","sizes":[]},"image_opacity":{"unit":"px","size":"","sizes":[]},"background_a_image":{"url":"https:\/\/library.elementor.com\/music-artist\/wp-content\/uploads\/sites\/116\/2020\/10\/album2.jpg","id":"96"},"background_b_color":"#000000BD","height":{"unit":"px","size":"530","sizes":[]},"flip_effect":"fade","title_color_b":"#FFFFFF","title_typography_b_typography":"custom","title_typography_b_font_family":"Anton","title_typography_b_font_size":{"unit":"px","size":"20","sizes":[]},"title_typography_b_font_weight":"400","title_typography_b_text_transform":"uppercase","title_typography_b_font_style":"normal","title_typography_b_line_height":{"unit":"px","size":"30","sizes":[]},"title_typography_b_letter_spacing":{"unit":"px","size":"1.33","sizes":[]},"description_color_b":"#FFFFFF","button_size":"xs","button_border_width":{"unit":"px","size":"0","sizes":[]},"button_border_radius":{"unit":"px","size":"0","sizes":[]},"__globals__":{"background_b_color":"globals\/colors?id=d615ad7","title_color_b":"globals\/colors?id=415489b","title_typography_b_typography":"globals\/typography?id=0fa9cde","description_color_b":"globals\/colors?id=415489b","description_typography_b_typography":"globals\/typography?id=secondary","button_typography_typography":"globals\/typography?id=accent","button_text_color":"globals\/colors?id=accent","button_background_color":"globals\/colors?id=secondary","button_hover_text_color":"globals\/colors?id=secondary","button_hover_background_color":"globals\/colors?id=accent"},"height_tablet":{"unit":"px","size":"250","sizes":[]},"height_mobile":{"unit":"px","size":"295","sizes":[]},"__dynamic__":{"link":"[elementor-tag id=\"8b3854a\" name=\"popup\" settings=\"%7B%22popup%22%3A%22120%22%7D\"]"}},"elements":[],"isInner":false,"widgetType":"flip-box","elType":"widget"},{"id":"5b8c5087","settings":{"graphic_element":"image","image":{"url":"","id":""},"image_size":"full","selected_icon":{"value":"","library":""},"title_text_a":"","description_text_a":"","background_a_background":"classic","background_a_position":"center center","background_a_repeat":"no-repeat","background_a_size":"cover","title_text_b":"2017","description_text_b":"Reality Check","button_text":"Listen","background_b_background":"classic","vertical_position_a":"middle","image_width":{"unit":"%","size":"100","sizes":[]},"image_opacity":{"unit":"px","size":"","sizes":[]},"background_a_image":{"url":"https:\/\/library.elementor.com\/music-artist\/wp-content\/uploads\/sites\/116\/2020\/10\/album4.jpg","id":"98"},"background_b_color":"#000000BD","height":{"unit":"px","size":"530","sizes":[]},"flip_effect":"fade","title_color_b":"#FFFFFF","title_typography_b_typography":"custom","title_typography_b_font_family":"Anton","title_typography_b_font_size":{"unit":"px","size":"20","sizes":[]},"title_typography_b_font_weight":"400","title_typography_b_text_transform":"uppercase","title_typography_b_font_style":"normal","title_typography_b_line_height":{"unit":"px","size":"30","sizes":[]},"title_typography_b_letter_spacing":{"unit":"px","size":"1.33","sizes":[]},"description_color_b":"#FFFFFF","button_size":"xs","button_border_width":{"unit":"px","size":"0","sizes":[]},"button_border_radius":{"unit":"px","size":"0","sizes":[]},"_margin":{"unit":"px","top":"40","right":"0","bottom":"0","left":"0","isLinked":""},"__globals__":{"background_b_color":"globals\/colors?id=d615ad7","title_color_b":"globals\/colors?id=415489b","title_typography_b_typography":"globals\/typography?id=0fa9cde","description_color_b":"globals\/colors?id=415489b","description_typography_b_typography":"globals\/typography?id=secondary","button_typography_typography":"globals\/typography?id=accent","button_text_color":"globals\/colors?id=accent","button_background_color":"globals\/colors?id=secondary","button_hover_text_color":"globals\/colors?id=secondary","button_hover_background_color":"globals\/colors?id=accent"},"height_tablet":{"unit":"px","size":"250","sizes":[]},"height_mobile":{"unit":"px","size":"295","sizes":[]},"__dynamic__":{"link":"[elementor-tag id=\"f241f27\" name=\"popup\" settings=\"%7B%22popup%22%3A%22120%22%7D\"]"}},"elements":[],"isInner":false,"widgetType":"flip-box","elType":"widget"},{"id":"6fb8770b","settings":{"graphic_element":"image","image":{"url":"","id":""},"image_size":"full","selected_icon":{"value":"","library":""},"title_text_a":"","description_text_a":"","background_a_background":"classic","background_a_position":"center center","background_a_repeat":"no-repeat","background_a_size":"cover","title_text_b":"2016","description_text_b":"9950","button_text":"Listen","background_b_background":"classic","vertical_position_a":"middle","image_width":{"unit":"%","size":"100","sizes":[]},"image_opacity":{"unit":"px","size":"","sizes":[]},"background_a_image":{"url":"https:\/\/library.elementor.com\/music-artist\/wp-content\/uploads\/sites\/116\/2020\/10\/album6.jpg","id":"100"},"background_b_color":"#000000BD","height":{"unit":"px","size":"530","sizes":[]},"flip_effect":"fade","title_color_b":"#FFFFFF","title_typography_b_typography":"custom","title_typography_b_font_family":"Anton","title_typography_b_font_size":{"unit":"px","size":"20","sizes":[]},"title_typography_b_font_weight":"400","title_typography_b_text_transform":"uppercase","title_typography_b_font_style":"normal","title_typography_b_line_height":{"unit":"px","size":"30","sizes":[]},"title_typography_b_letter_spacing":{"unit":"px","size":"1.33","sizes":[]},"description_color_b":"#FFFFFF","button_size":"xs","button_border_width":{"unit":"px","size":"0","sizes":[]},"button_border_radius":{"unit":"px","size":"0","sizes":[]},"_margin":{"unit":"px","top":"40","right":"0","bottom":"0","left":"0","isLinked":""},"__globals__":{"background_b_color":"globals\/colors?id=d615ad7","title_color_b":"globals\/colors?id=415489b","title_typography_b_typography":"globals\/typography?id=0fa9cde","description_color_b":"globals\/colors?id=415489b","description_typography_b_typography":"globals\/typography?id=secondary","button_typography_typography":"globals\/typography?id=accent","button_text_color":"globals\/colors?id=accent","button_background_color":"globals\/colors?id=secondary","button_hover_text_color":"globals\/colors?id=secondary","button_hover_background_color":"globals\/colors?id=accent"},"height_tablet":{"unit":"px","size":"250","sizes":[]},"height_mobile":{"unit":"px","size":"295","sizes":[]},"__dynamic__":{"link":"[elementor-tag id=\"465c1b8\" name=\"popup\" settings=\"%7B%22popup%22%3A%22120%22%7D\"]"}},"elements":[],"isInner":false,"widgetType":"flip-box","elType":"widget"}],"isInner":"","elType":"column"}],"isInner":"","elType":"section"}],"settings":{"template":"elementor_header_footer"},"metadata":[]}